pyqt_hidable_menubar/__init__.py
pyqt_hidable_menubar/hidableMenuBar.py
pyqt_hidable_menubar/ico/__init__.py
pyqt_hidable_menubar/ico/close.svg
pyqt_hidable_menubar-0.0.11.dist-info/LICENSE
pyqt_hidable_menubar-0.0.11.dist-info/METADATA
pyqt_hidable_menubar-0.0.11.dist-info/WHEEL
pyqt_hidable_menubar-0.0.11.dist-info/top_level.txt
pyqt_hidable_menubar-0.0.11.dist-info/RECORD
